flyteplugins/polars/__init__.py
flyteplugins/polars/df_transformer.py
flyteplugins_polars-2.0.0b53.dist-info/METADATA
flyteplugins_polars-2.0.0b53.dist-info/WHEEL
flyteplugins_polars-2.0.0b53.dist-info/entry_points.txt
flyteplugins_polars-2.0.0b53.dist-info/top_level.txt
flyteplugins_polars-2.0.0b53.dist-info/RECORD
