Metadata-Version: 2.4
Name: flyteplugins-polars
Version: 2.0.0b53
Summary: polars plugin for flyte
Author-email: Flyte Contributors <admin@flyte.org>
Requires-Python: >=3.10
Requires-Dist: polars
Requires-Dist: flyte
